orgz/__init__.py
orgz/orgz.py
orgz-0.1.dist-info/METADATA
orgz-0.1.dist-info/WHEEL
orgz-0.1.dist-info/entry_points.txt
orgz-0.1.dist-info/top_level.txt
orgz-0.1.dist-info/RECORD
