Metadata-Version: 2.1
Name: orgz
Version: 0.1
Summary: This is a widget designed for openGauss Database inspection Tool!
Home-page: https://github.com/Dannyrevenger/orgz.git
Author: DanielClover
Author-email: danielcaiyongjie@gmail.com
License: UNKNOWN
Platform: UNKNOWN
Classifier: Programming Language :: Python :: 3
Classifier: License :: OSI Approved :: MIT License
Classifier: Operating System :: OS Independent
Requires-Python: >=3.6
